vulturecov/__init__.py
vulturecov/__main__.py
vulturecov/cov_report.py
vulturecov/vulture_report.py
vulturecov-0.1.0.dist-info/METADATA
vulturecov-0.1.0.dist-info/WHEEL
vulturecov-0.1.0.dist-info/entry_points.txt
vulturecov-0.1.0.dist-info/RECORD
