Metadata-Version: 2.1
Name: vulturecov
Version: 0.1.0
Summary: Vulture and Coverage.py combined: Find dead code in your Python project.
Home-page: https://github.com/Jonas1312/vulturecov
License: WTFPL
Author: Jonas Maison
Author-email: Jonas1312@users.noreply.github.com
Requires-Python: >=3.8
Classifier: License :: Other/Proprietary License
Classifier: Programming Language :: Python :: 3
Classifier: Programming Language :: Python :: 3.8
Classifier: Programming Language :: Python :: 3.9
Classifier: Programming Language :: Python :: 3.10
Classifier: Programming Language :: Python :: 3.11
Requires-Dist: click (>=8.1.3,<9.0.0)
Project-URL: Repository, https://github.com/Jonas1312/vulturecov
